CHANGELOG.txt
LICENCE.txt
MANIFEST.in
README.txt
setup.py
functions/__init__.py
module_expander.egg-info/PKG-INFO
module_expander.egg-info/SOURCES.txt
module_expander.egg-info/dependency_links.txt
module_expander.egg-info/top_level.txt