Metadata-Version: 1.0
Name: module-expander
Version: 0.0.1
Summary: UNKNOWN
Home-page: UNKNOWN
Author: Ahmed Reda Hbaiz
Author-email: reda.hbaiiz@gmail.com
License: MIT
Keywords: expander
Platform: UNKNOWN
